modelingDash/__init__.py
modelingDash/appModeling.py
modelingDash/configModelisation.py
modelingDash/explorePumpTrialsDash.py
modelingDash/usefulCircuits.py
modelingDash/confFiles/Moulinette_preparation_manips_bruleur.xlsx
modelingDash/confFiles/copperConductivity-coeff-T.jpg
modelingDash/confFiles/logModeling.md
modelingDash/confFiles/materials.csv
modelingDash-1.3.10.dist-info/METADATA
modelingDash-1.3.10.dist-info/WHEEL
modelingDash-1.3.10.dist-info/top_level.txt
modelingDash-1.3.10.dist-info/RECORD
